silentwav/README.MD
silentwav/__init__.py
silentwav/requirements.txt
silentwav/thirdparty.json
silentwav-0.10.dist-info/LICENSE.rst
silentwav-0.10.dist-info/METADATA
silentwav-0.10.dist-info/WHEEL
silentwav-0.10.dist-info/top_level.txt
silentwav-0.10.dist-info/RECORD
