Metadata-Version: 2.1
Name: silentwav
Version: 0.10
Summary: Creates a silent WAV file with the specified duration and saves it to the given filename.
Home-page: https://github.com/hansalemaos/silentwav
Author: Johannes Fischer
Author-email: aulasparticularesdealemaosp@gmail.com
License: MIT
Keywords: wav,silent
Classifier: Development Status :: 4 - Beta
Classifier: Programming Language :: Python :: 3 :: Only
Classifier: Programming Language :: Python :: 3.10
Classifier: Topic :: Software Development :: Libraries :: Python Modules
Classifier: Topic :: Utilities
License-File: LICENSE.rst
Requires-Dist: touchtouch
